README.md
setup.py
src/testgear.py
src/testgear_python_commons/__init__.py
src/testgear_python_commons/app_properties.py
src/testgear_python_commons/decorators.py
src/testgear_python_commons/dynamic_methods.py
src/testgear_python_commons/step.py
src/testgear_python_commons.egg-info/PKG-INFO
src/testgear_python_commons.egg-info/SOURCES.txt
src/testgear_python_commons.egg-info/dependency_links.txt
src/testgear_python_commons.egg-info/requires.txt
src/testgear_python_commons.egg-info/top_level.txt
src/testgear_python_commons/client/__init__.py
src/testgear_python_commons/client/api_client.py
src/testgear_python_commons/client/client_configuration.py
src/testgear_python_commons/client/converter.py
src/testgear_python_commons/models/__init__.py
src/testgear_python_commons/models/adapter_mode.py
src/testgear_python_commons/models/link.py
src/testgear_python_commons/models/link_type.py
src/testgear_python_commons/models/outcome_type.py
src/testgear_python_commons/models/step_result.py
src/testgear_python_commons/models/test_result.py
src/testgear_python_commons/models/test_result_with_all_fixture_step_results_model.py
src/testgear_python_commons/services/__init__.py
src/testgear_python_commons/services/adapter_manager.py
src/testgear_python_commons/services/adapter_manager_configuration.py
src/testgear_python_commons/services/logger.py
src/testgear_python_commons/services/plugin_manager.py
src/testgear_python_commons/services/step_manager.py
src/testgear_python_commons/services/step_result_storage.py
src/testgear_python_commons/services/utils.py